memcached_search/__init__.py
memcached_search/main.py
memcached_search-0.1.dist-info/METADATA
memcached_search-0.1.dist-info/RECORD
memcached_search-0.1.dist-info/WHEEL
memcached_search-0.1.dist-info/entry_points.txt
memcached_search-0.1.dist-info/top_level.txt
