Metadata-Version: 2.1
Name: memcached-search
Version: 0.1
Summary: A simple tools for finding keys/values in a memcached server or cluster
Home-page: UNKNOWN
Author: Jason DeWitt
Author-email: jason.dewitt@10up.com
License: UNKNOWN
Platform: UNKNOWN
Classifier: Programming Language :: Python :: 3
Classifier: License :: OSI Approved :: MIT License
Classifier: Operating System :: OS Independent
Requires-Dist: Click
Requires-Dist: pymemcache
Requires-Dist: future
Requires-Dist: future-fstrings
